{
  "name": "Darrell Nelson",
  "age": 37,
  "address": {
    "street": "Adecu Road",
    "city": "Acuwizu",
    "state": "TN",
    "zip": "22182"
  },
  "contact": {
    "phone": "(375) 864-1241",
    "servicePhone": "800732337"
  },
  "birthday": "1977-02-12T01:03:39.162Z",
  "ip": "130.19.35.199",
  "foo": "bar",
  "profile": {
    "about": "No douse fales mita weparajus tusadav lupwotpa ridga cievolaf joj dec zum akesis guza hudah. Jaji tapabwot ri wo apatin ucigow git iriemo up ufwefem ozhegaj af. Muzuk fugo kelilbaw zezwan pedza rilahmi rofa bagebil aknof uc jooh izu vetgu fan zadvonawe duvomma.",
    "bio": "Nez tut levji cewuwezet go mozij wiw omer lubwehtuz zueca dugitgad za uv. Raf ehfijid omigito kasfemum gezas gupsac fog adtoiri ewzidpo ze nopvefev ju jacufu mepun zowlate gusenoc puk. Kofka fuidzag hi hetporpe wo lulvuchuz jij ladsil gighej bohbi abahap ishu cek zoeko ro. Vojnosro vasehoni caen pu powenak titufzo jatow vas wuwikca goceli oma ok occat ta ifoce om wettuk ate. Tedri ewerot teg epepuja tata joba jek gowaruuz kori ka gezijef rani ozi."
  },
  "apiKey": "c372376ca26e3d25edcd45e664224da09ad58dec58a9d2589a57e435dc05a6e1",
  "currency": {
    "code": "TOP",
    "name": "Tonga Pa'anga"
  }
}