{
  "name": "Lenora Webb",
  "age": 63,
  "address": {
    "street": "Wafkad Place",
    "city": "Kikbijga",
    "state": "FL",
    "zip": "24438"
  },
  "contact": {
    "phone": "(877) 486-3319",
    "servicePhone": "800943779"
  },
  "birthday": "1986-01-01T06:05:27.070Z",
  "ip": "24.101.94.229",
  "foo": "bar",
  "profile": {
    "about": "Mewep huw wugmujalo ub afrod kesfa silowol ojucu afpuk rultomatu hej tutu ebfunzu bekel buehisel. Ha lovdim wa dusiv uz gid se neligab ziljargur obha ec fukalwoj pagsule. Te er fotazeh sa wi zipremvon davren olsowne faf igo opupem vot ho monar oleamo cu. Ij ubrutub pinbem etate efi annan narlik pubog batreda ahokuli dotdib ivo wo vuvsu seewe evhovjav uhe moragod. Zuegovic onakij pepoj judu oppadhi zojdospak foz pegvecruf ih nihe nanopa irga nomuv pufil jew wenum.",
    "bio": "Boseme reizu hoz keve tudcenduz tealimok rag pube kejde toimeti wopfaku apin awhetag jagim. Edeiwsi famite foh udeziw juk biefi vagmafwo lesgolac vec zubbed todenze vacti. Wuzsa ciog olhon juwsop jizdevku baafja akekazib cofsivet ezbohzul holi ta foudegop gaporbug jenpo ucieta wiop je cuk. Lidohu cijaf ror sidtic ho si aviditeg na riwocaca op pammid walsahki vofofvi ebmudi uniap. Vilof suk huz dakwam voj faijrow utolle kenazmow pahepo lo siral reave bolgug zudso habodiwi."
  },
  "apiKey": "83db8070a8f9813331094f2e50acbb6a60973d1701d527cd008fea509c3ea7d3",
  "currency": {
    "code": "NZD",
    "name": "New Zealand Dollar"
  }
}